pymatlie/__init__.py
pymatlie/base_group.py
pymatlie/py.typed
pymatlie/se2.py
pymatlie/so2.py
pymatlie/vecops.py
pymatlie-0.0.1a1.dist-info/METADATA
pymatlie-0.0.1a1.dist-info/WHEEL
pymatlie-0.0.1a1.dist-info/licenses/LICENSE
pymatlie-0.0.1a1.dist-info/RECORD
