Metadata-Version: 2.4
Name: pymatlie
Version: 0.0.1a1
Summary: pymatlie provides an implementation of Matrix Lie Groups (MLG) used in robotics.
Project-URL: Homepage, https://github.com/luis-marques/pymatlie
Project-URL: Issues, https://github.com/luis-marques/pymatlie/issues
Author-email: Luis Marques <lmarques@umich.edu>
License-Expression: MIT
License-File: LICENSE
Classifier: Operating System :: OS Independent
Classifier: Programming Language :: Python :: 3
Requires-Python: >=3.9
Requires-Dist: torch>=2.1
Provides-Extra: dev
Requires-Dist: black; extra == 'dev'
Requires-Dist: docformatter; extra == 'dev'
Requires-Dist: isort; extra == 'dev'
Requires-Dist: lark; extra == 'dev'
Requires-Dist: mypy; extra == 'dev'
Requires-Dist: pylint>=2.14.5; extra == 'dev'
Requires-Dist: pytest-pylint>=0.18.0; extra == 'dev'
Requires-Dist: pytest>=7.2.2; extra == 'dev'
Requires-Dist: pyyaml; extra == 'dev'
